istmo_email_checker/__init__.py
istmo_email_checker/email/utils.py
istmo_email_checker/email/verify.py
istmo_email_checker-0.1.0.dist-info/METADATA
istmo_email_checker-0.1.0.dist-info/WHEEL
istmo_email_checker-0.1.0.dist-info/RECORD
