Metadata-Version: 2.1
Name: istmo-email-checker
Version: 0.1.0
Summary: Email validator
Author: dcampos
Author-email: dcampos@istmocenter.com
Requires-Python: >=3.9,<4.0
Classifier: Programming Language :: Python :: 3
Classifier: Programming Language :: Python :: 3.9
Classifier: Programming Language :: Python :: 3.10
Classifier: Programming Language :: Python :: 3.11
Requires-Dist: dnspython (>=2.4.2,<3.0.0)
